radinitio/__init__.py
radinitio/__main__.py
radinitio-1.2.3.data/scripts/radinitio
radinitio-1.2.3.dist-info/LICENSE
radinitio-1.2.3.dist-info/METADATA
radinitio-1.2.3.dist-info/WHEEL
radinitio-1.2.3.dist-info/top_level.txt
radinitio-1.2.3.dist-info/RECORD
