Metadata-Version: 2.1
Name: radinitio
Version: 1.2.3
Summary: A package for the simulation of RADseq data.
Home-page: http://catchenlab.life.illinois.edu/radinitio
Author: Angel G. Rivera-Colon <arcolon14@gmail.com>, Nicolas Rochette <rochette@illinois.edu>, Julian Catchen <jcatchen@illinois.edu>
Author-email: arcolon14@gmail.com
Project-URL: Manual, http://catchenlab.life.illinois.edu/radinitio/manual/
Project-URL: Source, https://bitbucket.org/angelgr2/radinitio/src/default/
Classifier: Programming Language :: Python :: 3
Classifier: License :: OSI Approved :: GNU General Public License (GPL)
Classifier: Operating System :: POSIX :: Linux
Requires-Python: >=3.9.0
License-File: LICENSE
Requires-Dist: scipy
Requires-Dist: numpy
Requires-Dist: decoratio
Requires-Dist: msprime
